pydantic_views/__init__.py
pydantic_views/annotations.py
pydantic_views/builder.py
pydantic_views/manager.py
pydantic_views/py.typed
pydantic_views/view.py
pydantic_views-0.3.0.dist-info/WHEEL
pydantic_views-0.3.0.dist-info/METADATA
pydantic_views-0.3.0.dist-info/RECORD
