Metadata-Version: 2.4
Name: pydantic-views
Version: 0.3.0
Summary: Views for Pydantic models
Keywords: view,pydantic,datamodel,model,REST API
Author: Alfred
Author-email: Alfred <alfred82santa@gmail.com>
License-Expression: MIT
Classifier: Development Status :: 4 - Beta
Classifier: Framework :: Pydantic
Classifier: Framework :: Pydantic :: 2
Classifier: Programming Language :: Python :: 3
Classifier: Programming Language :: Python :: 3.13
Classifier: Typing :: Typed
Requires-Dist: pydantic>=2.10.6,<3.0.0
Requires-Python: >=3.13, <4.0.0
Project-URL: Homepage, https://pydantic-views.readthedocs.io/stable/
Project-URL: Repository, https://github.com/alfred82santa/pydantic-views.git
Project-URL: Documentation, https://pydantic-views.readthedocs.io/stable/
Project-URL: Issues, https://github.com/alfred82santa/pydantic-views/issues
